knowledge_core_engine/__init__.py
knowledge_core_engine/engine.py
knowledge_core_engine/api/__init__.py
knowledge_core_engine/api/app.py
knowledge_core_engine/core/__init__.py
knowledge_core_engine/core/config.py
knowledge_core_engine/core/rag_pipeline.py
knowledge_core_engine/core/chunking/__init__.py
knowledge_core_engine/core/chunking/base.py
knowledge_core_engine/core/chunking/chunk_agent.py
knowledge_core_engine/core/chunking/enhanced_chunker.py
knowledge_core_engine/core/chunking/markdown_chunker.py
knowledge_core_engine/core/chunking/pipeline.py
knowledge_core_engine/core/chunking/smart_chunker.py
knowledge_core_engine/core/embedding/__init__.py
knowledge_core_engine/core/embedding/base.py
knowledge_core_engine/core/embedding/chroma_agent.py
knowledge_core_engine/core/embedding/embedder.py
knowledge_core_engine/core/embedding/multimodal_embedder.py
knowledge_core_engine/core/embedding/strategies.py
knowledge_core_engine/core/embedding/vector_store.py
knowledge_core_engine/core/enhancement/__init__.py
knowledge_core_engine/core/enhancement/metadata_enhancer.py
knowledge_core_engine/core/evaluation/__init__.py
knowledge_core_engine/core/evaluation/evaluator.py
knowledge_core_engine/core/evaluation/golden_dataset.py
knowledge_core_engine/core/evaluation/metrics.py
knowledge_core_engine/core/evaluation/ragas_adapter.py
knowledge_core_engine/core/evaluation/ragas_evaluator.py
knowledge_core_engine/core/evaluation/report_generator.py
knowledge_core_engine/core/generation/__init__.py
knowledge_core_engine/core/generation/citation_manager.py
knowledge_core_engine/core/generation/generator.py
knowledge_core_engine/core/generation/prompt_builder.py
knowledge_core_engine/core/generation/providers/__init__.py
knowledge_core_engine/core/generation/providers/deepseek.py
knowledge_core_engine/core/generation/providers/openai.py
knowledge_core_engine/core/generation/providers/qwen.py
knowledge_core_engine/core/parsing/__init__.py
knowledge_core_engine/core/parsing/base.py
knowledge_core_engine-0.3.1.dist-info/METADATA
knowledge_core_engine-0.3.1.dist-info/WHEEL
knowledge_core_engine-0.3.1.dist-info/entry_points.txt
knowledge_core_engine-0.3.1.dist-info/top_level.txt
knowledge_core_engine-0.3.1.dist-info/RECORD
