Metadata-Version: 2.4
Name: knowledge-core-engine
Version: 0.3.1
Summary: Next-generation knowledge base engine with advanced RAG capabilities
Author-email: Zephyr Sailor <zephyrsailor0715@gmail.com>
License: MIT
Project-URL: Homepage, https://github.com/zephyrsailor/knowledge-core-engine
Project-URL: Bug Reports, https://github.com/zephyrsailor/knowledge-core-engine/issues
Project-URL: Source, https://github.com/zephyrsailor/knowledge-core-engine
Classifier: Development Status :: 3 - Alpha
Classifier: Intended Audience :: Developers
Classifier: License :: OSI Approved :: MIT License
Classifier: Programming Language :: Python :: 3
Classifier: Programming Language :: Python :: 3.9
Classifier: Programming Language :: Python :: 3.10
Classifier: Programming Language :: Python :: 3.11
Classifier: Programming Language :: Python :: 3.12
Classifier: Topic :: Software Development :: Libraries :: Python Modules
Classifier: Topic :: Scientific/Engineering :: Artificial Intelligence
Requires-Python: >=3.9
Requires-Dist: llama-index>=0.10.0
Requires-Dist: llama-index-llms-openai>=0.1.0
Requires-Dist: llama-index-embeddings-dashscope>=0.1.0
Requires-Dist: llama-index-vector-stores-chroma>=0.1.0
Requires-Dist: llama-parse>=0.4.0
Requires-Dist: fastapi>=0.110.0
Requires-Dist: uvicorn[standard]>=0.27.0
Requires-Dist: pydantic>=2.5.0
Requires-Dist: pydantic-settings>=2.1.0
Requires-Dist: chromadb>=0.4.22
Requires-Dist: pymupdf>=1.23.0
Requires-Dist: python-docx>=1.1.0
Requires-Dist: beautifulsoup4>=4.12.0
Requires-Dist: markdownify>=0.11.0
Requires-Dist: bm25s>=0.1.0
Requires-Dist: mineru[core]>=0.2.0
Requires-Dist: dashscope>=1.14.0
Requires-Dist: openai>=1.12.0
Requires-Dist: python-dotenv>=1.0.0
Requires-Dist: httpx>=0.26.0
Requires-Dist: tenacity>=8.2.0
Requires-Dist: loguru>=0.7.0
Requires-Dist: tqdm>=4.66.0
Requires-Dist: ragas>=0.1.0
Requires-Dist: pandas>=2.0.0
Requires-Dist: numpy>=1.24.0
Requires-Dist: reportlab>=4.4.3
Provides-Extra: dev
Requires-Dist: pytest>=7.4.0; extra == "dev"
Requires-Dist: pytest-asyncio>=0.23.0; extra == "dev"
Requires-Dist: pytest-cov>=4.1.0; extra == "dev"
Requires-Dist: pytest-mock>=3.12.0; extra == "dev"
Requires-Dist: ruff>=0.1.0; extra == "dev"
Requires-Dist: mypy>=1.8.0; extra == "dev"
Requires-Dist: pre-commit>=3.6.0; extra == "dev"
Requires-Dist: mkdocs>=1.5.0; extra == "dev"
Requires-Dist: mkdocs-material>=9.5.0; extra == "dev"
Requires-Dist: mkdocstrings[python]>=0.24.0; extra == "dev"
Provides-Extra: huggingface
Requires-Dist: transformers>=4.36.0; extra == "huggingface"
Requires-Dist: torch>=2.1.0; extra == "huggingface"
Requires-Dist: sentence-transformers>=2.3.0; extra == "huggingface"
Provides-Extra: reranker-hf
Requires-Dist: transformers>=4.36.0; extra == "reranker-hf"
Requires-Dist: torch>=2.1.0; extra == "reranker-hf"
Requires-Dist: FlagEmbedding>=1.2.0; extra == "reranker-hf"
Requires-Dist: sentence-transformers>=2.2.0; extra == "reranker-hf"
Provides-Extra: elasticsearch
Requires-Dist: elasticsearch>=8.0.0; extra == "elasticsearch"
